faisal_salahi_calculator/__init__.py
faisal_salahi_calculator/calculator.py
faisal_salahi_calculator-0.1.0.dist-info/licenses/LICENSE
faisal_salahi_calculator-0.1.0.dist-info/METADATA
faisal_salahi_calculator-0.1.0.dist-info/WHEEL
faisal_salahi_calculator-0.1.0.dist-info/top_level.txt
faisal_salahi_calculator-0.1.0.dist-info/RECORD
