Metadata-Version: 2.4
Name: faisal_salahi_calculator
Version: 0.1.0
Summary: آلة حاسبة بسيطة لإجراء العمليات الحسابية الأساسية
Home-page: https://github.com/faisalsalahi/faisal-salahi-calculator
Author: فيصل الصلاحي
Author-email: فيصل الصلاحي <contact@faisalsalahi.com>
License: MIT License
Project-URL: Homepage, https://github.com/faisalsalahi/faisal-salahi-calculator
Project-URL: Bug Reports, https://github.com/faisalsalahi/faisal-salahi-calculator/issues
Project-URL: Source, https://github.com/faisalsalahi/faisal-salahi-calculator
Keywords: calculator,math,arithmetic,حاسبة,رياضيات
Classifier: Development Status :: 4 - Beta
Classifier: Intended Audience :: Developers
Classifier: Intended Audience :: Education
Classifier: Topic :: Scientific/Engineering :: Mathematics
Classifier: Topic :: Software Development :: Libraries :: Python Modules
Classifier: License :: OSI Approved :: MIT License
Classifier: Programming Language :: Python :: 3
Classifier: Programming Language :: Python :: 3.6
Classifier: Programming Language :: Python :: 3.7
Classifier: Programming Language :: Python :: 3.8
Classifier: Programming Language :: Python :: 3.9
Classifier: Programming Language :: Python :: 3.10
Classifier: Programming Language :: Python :: 3.11
Classifier: Operating System :: OS Independent
Requires-Python: >=3.6
License-File: LICENSE
Provides-Extra: dev
Requires-Dist: pytest>=6.0; extra == "dev"
Requires-Dist: pytest-cov; extra == "dev"
Requires-Dist: black; extra == "dev"
Requires-Dist: flake8; extra == "dev"
Dynamic: author
Dynamic: home-page
Dynamic: license-file
Dynamic: requires-python
